MANIFEST.in
README.markdown
setup.py
ckanext/__init__.py
ckanext/datapackager/__init__.py
ckanext/datapackager/exceptions.py
ckanext/datapackager/plugin.py
ckanext/datapackager/controllers/__init__.py
ckanext/datapackager/controllers/datapackage.py
ckanext/datapackager/lib/__init__.py
ckanext/datapackager/lib/converter.py
ckanext/datapackager/lib/util.py
ckanext/datapackager/logic/__init__.py
ckanext/datapackager/logic/action/__init__.py
ckanext/datapackager/logic/action/create.py
ckanext/datapackager/logic/action/get.py
ckanext/datapackager/templates/datapackage/import_datapackage.html
ckanext/datapackager/templates/datapackage/snippets/import_datapackage_basic_fields.html
ckanext/datapackager/templates/datapackage/snippets/import_datapackage_form.html
ckanext/datapackager/templates/organization/read.html
ckanext/datapackager/templates/package/read.html
ckanext/datapackager/templates/package/search.html
ckanext/datapackager/templates/user/dashboard_datasets.html
ckanext/datapackager/tests/__init__.py
ckanext/datapackager/tests/helpers.py
ckanext/datapackager/tests/controllers/__init__.py
ckanext/datapackager/tests/controllers/test_datapackage.py
ckanext/datapackager/tests/lib/__init__.py
ckanext/datapackager/tests/lib/test_converter.py
ckanext/datapackager/tests/lib/test_util.py
ckanext/datapackager/tests/logic/__init__.py
ckanext/datapackager/tests/logic/action/__init__.py
ckanext/datapackager/tests/logic/action/test_create.py
ckanext/datapackager/tests/logic/action/test_get.py
ckanext_datapackager.egg-info/PKG-INFO
ckanext_datapackager.egg-info/SOURCES.txt
ckanext_datapackager.egg-info/dependency_links.txt
ckanext_datapackager.egg-info/entry_points.txt
ckanext_datapackager.egg-info/namespace_packages.txt
ckanext_datapackager.egg-info/not-zip-safe
ckanext_datapackager.egg-info/pbr.json
ckanext_datapackager.egg-info/requires.txt
ckanext_datapackager.egg-info/top_level.txt