Metadata-Version: 1.1
Name: ckanext-datapackager
Version: 0.2.0
Summary: This extension adds importing and exporting of Data Packages to CKAN datasets.
Home-page: https://github.com/ckan/ckanext-datapackager
Author: Open Knowledge International
Author-email: info@okfn.org
License: AGPL
Keywords: CKAN datapackages
Platform: UNKNOWN
Classifier: Development Status :: 4 - Beta
Classifier: License :: OSI Approved :: GNU Affero General Public License v3 or later (AGPLv3+)
Classifier: Programming Language :: Python :: 2.7
